{
  "element_list": [
    {
      "type": "Barrack",
      "builder_path": "../Resource/builder/barrack.json",
      "paramater": {
        "type": "Fence",
        "name": "Fence",
        "tag": "Untagged",
        "tags": [
        ]
      },
      "transform": {
        "position": [
          0.0,
          -5.0,
          0.0
        ],
        "rotation": [
          0.0,
          0.0,
          0.0
        ],
        "scale": [
          1.0,
          1.0,
          1.0
        ]
      }
    }
  ]
}